MANIFEST.in
README.md
setup.py
brighterflame/__init__.py
brighterflame.egg-info/PKG-INFO
brighterflame.egg-info/SOURCES.txt
brighterflame.egg-info/dependency_links.txt
brighterflame.egg-info/not-zip-safe
brighterflame.egg-info/requires.txt
brighterflame.egg-info/top_level.txt