Metadata-Version: 2.1
Name: brighterflame
Version: 0.0.0
Summary: Speed up your deep pytorch models with sound optimization procedures!
Home-page: https://gitlab.com/dbalboni/brighterflame
Author: Dario Balboni
Author-email: dario.balboni.96@gmail.com
License: PROPRIETARY
Keywords: pytorch optimization deep-learning
Platform: UNKNOWN
Classifier: License :: Other/Proprietary License
Requires-Python: >=3.9
